setup.cfg
setup.py
noderoot/__init__.py
noderoot/__main__.py
noderoot/log.py
noderoot/logging_subprocess.py
noderoot/nfs.py
noderoot/ssh_helpers.py
noderoot.egg-info/PKG-INFO
noderoot.egg-info/SOURCES.txt
noderoot.egg-info/dependency_links.txt
noderoot.egg-info/entry_points.txt
noderoot.egg-info/requires.txt
noderoot.egg-info/top_level.txt