Metadata-Version: 1.1
Name: noderoot
Version: 0.0.2
Summary: Noderoot is a tool for chrooting into root file systems stored on a different system.
Home-page: https://github.com/gusbricker/noderoot
Author: Chris Lapa
Author-email: chris@lapa.com.au
License: GPLv2
Download-URL: https://github.com/gusbricker/noderoot/tarball/0.0.2
Keywords: rootfs development linux
Platform: UNKNOWN
Classifier: Development Status :: 3 - Alpha
Classifier: Intended Audience :: Developers
Classifier: Topic :: Software Development :: Build Tools
Classifier: License :: OSI Approved :: MIT License
Classifier: Programming Language :: Python :: 2.7
